{
  "processing_timestamp": "2025-10-27T12:35:18.054109",
  "source_file": "TechArena2025_Phase2_data.xlsx",
  "data_counts": {
    "day_ahead": 35136,
    "fcr": 2197,
    "afrr_capacity": 2197,
    "afrr_energy": 35136
  },
  "date_range": {
    "start": "2024-01-01T00:00:00",
    "end": "2024-12-31T23:45:10.119000"
  },
  "columns": {
    "day_ahead": [
      "timestamp",
      "DE_LU",
      "AT",
      "CH",
      "HU",
      "CZ"
    ],
    "fcr": [
      "timestamp",
      "DE",
      "AT",
      "CH",
      "HU",
      "CZ"
    ],
    "afrr_capacity": [
      "timestamp",
      "DE_Pos",
      "DE_Neg",
      "AT_Pos",
      "AT_Neg",
      "CH_Pos",
      "CH_Neg",
      "HU_Pos",
      "HU_Neg",
      "CZ_Pos",
      "CZ_Neg"
    ],
    "afrr_energy": [
      "timestamp",
      "DE_Pos",
      "DE_Neg",
      "AT_Pos",
      "AT_Neg",
      "CH_Pos",
      "CH_Neg",
      "HU_Pos",
      "HU_Neg",
      "CZ_Pos",
      "CZ_Neg"
    ]
  },
  "validation": {
    "passed": true,
    "errors_count": 0,
    "warnings_count": 4,
    "errors": [],
    "warnings": [
      "day_ahead: Found 10119 timestamp gaps (largest: 0 days 00:15:00.001000)",
      "fcr: Found 632 timestamp gaps (largest: 0 days 04:00:00.001000)",
      "afrr_capacity: Found 632 timestamp gaps (largest: 0 days 04:00:00.001000)",
      "afrr_energy: Found 10119 timestamp gaps (largest: 0 days 00:15:00.001000)"
    ]
  },
  "statistics": {
    "day_ahead_gaps": 10119,
    "fcr_gaps": 632,
    "afrr_capacity_gaps": 632,
    "afrr_energy_gaps": 10119,
    "day_ahead.DE_LU_min": -499.99,
    "day_ahead.DE_LU_max": 1398.02,
    "day_ahead.DE_LU_mean": 77.84024390938067,
    "day_ahead.AT_min": -177.82,
    "day_ahead.AT_max": 709.0,
    "day_ahead.AT_mean": 80.89204092668488,
    "day_ahead.CH_min": -427.51,
    "day_ahead.CH_max": 310.64,
    "day_ahead.CH_mean": 75.95615095628415,
    "day_ahead.HU_min": -149.98,
    "day_ahead.HU_max": 999.01,
    "day_ahead.HU_mean": 100.81302823315117,
    "day_ahead.CZ_min": -138.75,
    "day_ahead.CZ_max": 844.63,
    "day_ahead.CZ_mean": 85.10506261384334,
    "fcr.DE_min": 17.2,
    "fcr.DE_max": 360.0,
    "fcr.DE_mean": 65.06425125170688,
    "fcr.AT_min": 17.2,
    "fcr.AT_max": 360.0,
    "fcr.AT_mean": 65.30533909877106,
    "fcr.CH_min": 17.21,
    "fcr.CH_max": 360.0,
    "fcr.CH_mean": 64.35271109082609,
    "fcr.HU_min": 3.185108070592901,
    "fcr.HU_max": 20.835812016656753,
    "fcr.HU_mean": 11.973471025827857,
    "fcr.CZ_min": 17.2,
    "fcr.CZ_max": 1600.0,
    "fcr.CZ_mean": 104.64816568047338,
    "afrr_capacity.DE_Pos_min": 1.86,
    "afrr_capacity.DE_Pos_max": 176.64,
    "afrr_capacity.DE_Pos_mean": 13.137410104688211,
    "afrr_capacity.DE_Neg_min": 0.32,
    "afrr_capacity.DE_Neg_max": 88.71,
    "afrr_capacity.DE_Neg_mean": 10.840436959490216,
    "afrr_capacity.AT_Pos_min": 1.6,
    "afrr_capacity.AT_Pos_max": 174.81,
    "afrr_capacity.AT_Pos_mean": 11.153823395539375,
    "afrr_capacity.AT_Neg_min": 0.25,
    "afrr_capacity.AT_Neg_max": 56.03,
    "afrr_capacity.AT_Neg_mean": 6.529849795175239,
    "afrr_capacity.CH_Pos_min": 2.11,
    "afrr_capacity.CH_Pos_max": 1057.48,
    "afrr_capacity.CH_Pos_mean": 18.42336822940373,
    "afrr_capacity.CH_Neg_min": 0.43,
    "afrr_capacity.CH_Neg_max": 285.97,
    "afrr_capacity.CH_Neg_mean": 14.540409649522076,
    "afrr_capacity.HU_Pos_min": 0.0,
    "afrr_capacity.HU_Pos_max": 12.069648783870807,
    "afrr_capacity.HU_Pos_mean": 2.133816453844312,
    "afrr_capacity.HU_Neg_min": 0.0,
    "afrr_capacity.HU_Neg_max": 21.53613711794719,
    "afrr_capacity.HU_Neg_mean": 3.5492970042798966,
    "afrr_capacity.CZ_Pos_min": 4.296075496688741,
    "afrr_capacity.CZ_Pos_max": 2874.0148277551016,
    "afrr_capacity.CZ_Pos_mean": 57.52698050731889,
    "afrr_capacity.CZ_Neg_min": 0.03499444759206799,
    "afrr_capacity.CZ_Neg_max": 38.58412691218131,
    "afrr_capacity.CZ_Neg_mean": 1.359959525050474,
    "afrr_energy.DE_Pos_min": 0.0,
    "afrr_energy.DE_Pos_max": 600.0,
    "afrr_energy.DE_Pos_mean": 99.71472635526446,
    "afrr_energy.DE_Neg_min": 0.0,
    "afrr_energy.DE_Neg_max": 599.0,
    "afrr_energy.DE_Neg_mean": 45.989102081452764,
    "afrr_energy.AT_Pos_min": 0.0,
    "afrr_energy.AT_Pos_max": 600.0,
    "afrr_energy.AT_Pos_mean": 123.12598047586522,
    "afrr_energy.AT_Neg_min": 0.0,
    "afrr_energy.AT_Neg_max": 430.0,
    "afrr_energy.AT_Neg_mean": 16.468477629781418,
    "afrr_energy.CH_Pos_min": 0.0,
    "afrr_energy.CH_Pos_max": 600.0,
    "afrr_energy.CH_Pos_mean": 196.25227658242255,
    "afrr_energy.CH_Neg_min": 0.0,
    "afrr_energy.CH_Neg_max": 600.0,
    "afrr_energy.CH_Neg_mean": 56.15674094945355,
    "afrr_energy.HU_Pos_min": 0.0,
    "afrr_energy.HU_Pos_max": 600.0,
    "afrr_energy.HU_Pos_mean": 115.87783039839455,
    "afrr_energy.HU_Neg_min": 0.0,
    "afrr_energy.HU_Neg_max": 573.0,
    "afrr_energy.HU_Neg_mean": 4.687794664203224,
    "afrr_energy.CZ_Pos_min": 0.0,
    "afrr_energy.CZ_Pos_max": 600.0,
    "afrr_energy.CZ_Pos_mean": 111.77172045765028,
    "afrr_energy.CZ_Neg_min": 0.0,
    "afrr_energy.CZ_Neg_max": 596.0,
    "afrr_energy.CZ_Neg_mean": 49.597051172586525,
    "afrr_energy.DE_Pos_zero_pct": 5.806010928961749,
    "afrr_energy.DE_Neg_zero_pct": 22.663365209471767,
    "afrr_energy.AT_Pos_zero_pct": 8.785860655737705,
    "afrr_energy.AT_Neg_zero_pct": 33.51832877959927,
    "afrr_energy.CH_Pos_zero_pct": 0.7371357012750456,
    "afrr_energy.CH_Neg_zero_pct": 38.80066029143898,
    "afrr_energy.HU_Pos_zero_pct": 59.295309653916206,
    "afrr_energy.HU_Neg_zero_pct": 80.59255464480874,
    "afrr_energy.CZ_Pos_zero_pct": 3.2388433515482693,
    "afrr_energy.CZ_Neg_zero_pct": 23.767645719489984,
    "day_ahead_min_correlation": 0.5197000803306193
  }
}